README.md
setup.py
Grenadevisuals/__init__.py
Grenadevisuals.egg-info/PKG-INFO
Grenadevisuals.egg-info/SOURCES.txt
Grenadevisuals.egg-info/dependency_links.txt
Grenadevisuals.egg-info/top_level.txt