Metadata-Version: 2.1
Name: Grenadevisuals
Version: 0.0.1
Summary: Python async library for pulling news off of https://www.epicgames.com/fortnite/en-US/news
Home-page: https://github.com/BigBrain21/FortniteNewsGrabber
Author: Riley
License: UNKNOWN
Platform: UNKNOWN
Classifier: Programming Language :: Python :: 3
Classifier: License :: OSI Approved :: MIT License
Classifier: Operating System :: OS Independent
Requires-Python: >=3.6
